AUTHORS
CHANGES
LICENSE
MANIFEST
MANIFEST.in
Makefile
README.rst
requirements.txt
setup.py
docs/Makefile
docs/changes.rst
docs/conf.py
docs/index.rst
docs/make.bat
docs/redhat.rst
docs/servers.rst
docs/vmware.rst
docs/modules/brocade.rst
docs/modules/vmax.rst
docs/templates/layout.html
storage/__init__.py
storage/brocade.py
storage/servers.py
storage/ssh.py
storage/vmax.py
storage/vnx.py
storage.egg-info/PKG-INFO
storage.egg-info/SOURCES.txt
storage.egg-info/dependency_links.txt
storage.egg-info/requires.txt
storage.egg-info/top_level.txt
tests/__init__.py