Metadata-Version: 1.1
Name: storage
Version: 0.0.6a6
Summary: Libraries to interact with Enterprise Storage Arrays, FC Switches and Servers.
Home-page: https://github.com/OpenSRM/storage
Author: Srikanth Chundi
Author-email: srikanth912@gmail.com
License: This is the MIT license: http://www.opensource.org/licenses/mit-license.php
